conda_xdgpatch/__init__.py
conda_xdgpatch-0.2.dist-info/METADATA
conda_xdgpatch-0.2.dist-info/WHEEL
conda_xdgpatch-0.2.dist-info/entry_points.txt
conda_xdgpatch-0.2.dist-info/RECORD
