Metadata-Version: 2.1
Name: conda-xdgpatch
Version: 0.2
Summary: Patch for conda to use XDG-locations.
Home-page: https://github.com/libranet/conda-xdgpatch
License: MIT
Keywords: conda,xdg,sitecustomize
Author: Wouter Vanden Hove
Author-email: wouter@libranet.eu
Maintainer: Wouter Vanden Hove
Maintainer-email: wouter@libranet.eu
Requires-Python: >=3.8.0,<4.0
Classifier: Development Status :: 3 - Alpha
Classifier: Environment :: Console
Classifier: Intended Audience :: Developers
Classifier: License :: OSI Approved :: MIT License
Classifier: Operating System :: POSIX :: Linux
Classifier: Programming Language :: Python :: 3
Classifier: Programming Language :: Python :: 3.8
Classifier: Programming Language :: Python :: 3.9
Classifier: Programming Language :: Python :: 3.10
Classifier: Programming Language :: Python :: 3.11
Classifier: Programming Language :: Python :: Implementation :: CPython
Classifier: Programming Language :: Python :: Implementation :: PyPy
Classifier: Typing :: Typed
Requires-Dist: sitecustomize-entrypoints (>=0.1.0)
Project-URL: Bug Tracker, https://github.com/Libranet/conda-xdgpatch/issues
Project-URL: Documentation, https://github.com/libranet/conda-xdgpatch
Project-URL: Repository, https://github.com/libranet/conda-xdgpatch
